netsight.caseinsensitivefieldindex-configure.zcml
setup.cfg
setup.py
netsight/__init__.py
netsight.caseinsensitivefieldindex.egg-info/PKG-INFO
netsight.caseinsensitivefieldindex.egg-info/SOURCES.txt
netsight.caseinsensitivefieldindex.egg-info/dependency_links.txt
netsight.caseinsensitivefieldindex.egg-info/entry_points.txt
netsight.caseinsensitivefieldindex.egg-info/namespace_packages.txt
netsight.caseinsensitivefieldindex.egg-info/not-zip-safe
netsight.caseinsensitivefieldindex.egg-info/paster_plugins.txt
netsight.caseinsensitivefieldindex.egg-info/requires.txt
netsight.caseinsensitivefieldindex.egg-info/top_level.txt
netsight/caseinsensitivefieldindex/CaseInsensitiveFieldIndex.py
netsight/caseinsensitivefieldindex/README.txt
netsight/caseinsensitivefieldindex/__init__.py
netsight/caseinsensitivefieldindex/configure.zcml
netsight/caseinsensitivefieldindex/refresh.txt
netsight/caseinsensitivefieldindex/tests.py
netsight/caseinsensitivefieldindex/zope2.py
netsight/caseinsensitivefieldindex/dtml/addCaseInsensitiveFieldIndex.dtml
netsight/caseinsensitivefieldindex/dtml/manageCaseInsensitiveFieldIndex.dtml
netsight/caseinsensitivefieldindex/www/index.gif
