Metadata-Version: 1.0
Name: netsight.caseinsensitivefieldindex
Version: 0.1dev-r3746
Summary: A case insensitive version of Zope's FieldIndex
Home-page: http://www.netsight.co.uk/
Author: Matt Hamilton
Author-email: matth@netsight.co.uk
License: BSD
Keywords: zope indexing fieldindex
Platform: UNKNOWN
Classifier: Framework :: Plone
Classifier: Framework :: Zope2
Classifier: Framework :: Zope3
Classifier: Programming Language :: Python
Classifier: Topic :: Software Development :: Libraries :: Python Modules
